<Members><Member Member_Id="4358" Dods_Id="41314" Pims_Id="6126"><DisplayAs>Wendy Morton</DisplayAs><ListAs>Morton, Wendy</ListAs><FullTitle>Wendy Morton MP</FullTitle><LayingMinisterName/><DateOfBirth>1967-11-09T00:00:00</DateOfBirth><DateOfDeath xsi:nil="true" xmlns:xsi="http://www.w3.org/2001/XMLSchema-instance"/><Gender>F</Gender><Party Id="4">Conservative</Party><House>Commons</House><MemberFrom>Aldridge-Brownhills</MemberFrom><HouseStartDate>2015-05-07T00:00:00</HouseStartDate><HouseEndDate xsi:nil="true" xmlns:xsi="http://www.w3.org/2001/XMLSchema-instance"/><CurrentStatus Id="0" IsActive="True"><Name>Current Member</Name><Reason/><StartDate>2015-05-07T00:00:00</StartDate></CurrentStatus><BasicDetails><GivenSurname>Morton</GivenSurname><GivenMiddleNames/><GivenForename>Wendy</GivenForename><TownOfBirth/><CountryOfBirth/><Gender>F</Gender><DateOfBirth xsi:nil="true" xmlns:xsi="http://www.w3.org/2001/XMLSchema-instance"/><DateOfRetirement xsi:nil="true" xmlns:xsi="http://www.w3.org/2001/XMLSchema-instance"/><DateOfDeath xsi:nil="true" xmlns:xsi="http://www.w3.org/2001/XMLSchema-instance"/><LordsDetails/></BasicDetails><PreferredNames><PreferredName><Title/><Surname>Morton</Surname><MiddleNames/><Forename>Wendy</Forename><Suffix/><AddressAs>Wendy Morton</AddressAs><Note>Created at General Election</Note><StartDate>2015-05-07T00:00:00</StartDate><EndDate xsi:nil="true" xmlns:xsi="http://www.w3.org/2001/XMLSchema-instance"/><HonouraryPrefixes/></PreferredName></PreferredNames><HouseMemberships><HouseMembership><House>Commons</House><StartDate>2015-05-07T00:00:00</StartDate><EndDate xsi:nil="true" xmlns:xsi="http://www.w3.org/2001/XMLSchema-instance"/><EndReason/><EndNotes/></HouseMembership></HouseMemberships><Constituencies><Constituency Id="3290"><Name>Aldridge-Brownhills</Name><StartDate>2015-05-07T00:00:00</StartDate><EndDate xsi:nil="true" xmlns:xsi="http://www.w3.org/2001/XMLSchema-instance"/><Election Id="369"><Name>2015 General Election</Name><Date>2015-05-07T00:00:00</Date><Type>General Election</Type></Election><EndReason/><EntryType>First entry</EntryType><Notes/><SwearInOrder>127</SwearInOrder><SwornInForename/><SwornInMiddleNames/><SwornInSurname/><SwornInTitle/></Constituency></Constituencies><ElectionsContested/><MaidenSpeeches><MaidenSpeech><House>Commons</House><SpeechDate>2015-06-03T00:00:00</SpeechDate><Hansard>596 c651-3</Hansard><Subject>Debate on the Address (5th Day)</Subject></MaidenSpeech></MaidenSpeeches><Committees><Committee Id="98"><Name>International Development Committee</Name><StartDate>2015-07-08T00:00:00</StartDate><EndDate xsi:nil="true" xmlns:xsi="http://www.w3.org/2001/XMLSchema-instance"/><EndNote/><IsExOfficio>False</IsExOfficio><IsAlternate>False</IsAlternate><IsCoOpted>False</IsCoOpted><ChairDates/></Committee></Committees><GovernmentPosts/><OppositionPosts/><ParliamentaryPosts/><Statuses><Status Id="0"><Name>Current Member</Name><StartDate>2015-05-07T00:00:00</StartDate><EndDate xsi:nil="true" xmlns:xsi="http://www.w3.org/2001/XMLSchema-instance"/></Status></Statuses><Parties><Party Id="4"><Name>Conservative</Name><SubType/><StartDate>2015-05-07T00:00:00</StartDate><EndDate xsi:nil="true" xmlns:xsi="http://www.w3.org/2001/XMLSchema-instance"/><Note>Created at General Election</Note><SitsOppositeSideToParty>False</SitsOppositeSideToParty></Party></Parties><Honours/><OtherParliaments/><Interests><Category Id="18" Name="2. (a) Support linked to an MP but received by a local party organisation or indirectly via a central party organisation"><Interest Id="20155" ParentId="" LastAmendment="2015-06-03T15:33:38" LastAmendmentType="C"><RegisteredInterest>Name of donor: DM Electronics Ltd&#xD;
Address of donor: 4C Leyburn Business Park, Leyburn, North Yorkshire DL8 5QA&#xD;
Amount of donation or nature and value if donation in kind: £5,000&#xD;
Donor status: company, registration 02715837&#xD;
</RegisteredInterest><RegisteredLate>False</RegisteredLate><Created>2015-06-02T00:00:00</Created><Amended xsi:nil="true" xmlns:xsi="http://www.w3.org/2001/XMLSchema-instance"/><Deleted xsi:nil="true" xmlns:xsi="http://www.w3.org/2001/XMLSchema-instance"/><IsCorrection>False</IsCorrection><Notes/><ShowCreatedDateAsRegisteredDate>True</ShowCreatedDateAsRegisteredDate></Interest><Interest Id="20156" ParentId="" LastAmendment="2015-06-03T15:35:08" LastAmendmentType="C"><RegisteredInterest>Name of donor: United and Cecil Club&#xD;
Address of donor: Beckfield, Crouch Lane, Winkfield, Windsor, Berkshire SL4 4TN&#xD;
Amount of donation or nature and value if donation in kind: £5,000&#xD;
Donor status: members association&#xD;
</RegisteredInterest><RegisteredLate>False</RegisteredLate><Created>2015-06-02T00:00:00</Created><Amended xsi:nil="true" xmlns:xsi="http://www.w3.org/2001/XMLSchema-instance"/><Deleted xsi:nil="true" xmlns:xsi="http://www.w3.org/2001/XMLSchema-instance"/><IsCorrection>False</IsCorrection><Notes/><ShowCreatedDateAsRegisteredDate>True</ShowCreatedDateAsRegisteredDate></Interest><Interest Id="20157" ParentId="" LastAmendment="2015-06-03T15:36:22" LastAmendmentType="C"><RegisteredInterest>Name of donor: Unionist Buildings Ltd&#xD;
Address of donor: Arbor Chambers, 16 Broadway North, Walsall WS1 2NA&#xD;
Amount of donation or nature and value if donation in kind: £5,000&#xD;
Donor status: company, registration 00116945&#xD;
</RegisteredInterest><RegisteredLate>False</RegisteredLate><Created>2015-06-02T00:00:00</Created><Amended xsi:nil="true" xmlns:xsi="http://www.w3.org/2001/XMLSchema-instance"/><Deleted xsi:nil="true" xmlns:xsi="http://www.w3.org/2001/XMLSchema-instance"/><IsCorrection>False</IsCorrection><Notes/><ShowCreatedDateAsRegisteredDate>True</ShowCreatedDateAsRegisteredDate></Interest></Category><Category Id="24" Name="6. Land and property: (i) value over £100,000 (ii) rental income of over £10,000 a year"><Interest Id="20049" ParentId="" LastAmendment="2015-07-16T15:33:54" LastAmendmentType="U"><RegisteredInterest>Until 7 July 2015, cottage in North Yorkshire: (i) (Registered 6 June 2015; updated 14 July 2015)</RegisteredInterest><RegisteredLate>False</RegisteredLate><Created>2015-06-02T00:00:00</Created><Amended>2015-07-16T15:33:54</Amended><Deleted xsi:nil="true" xmlns:xsi="http://www.w3.org/2001/XMLSchema-instance"/><IsCorrection>False</IsCorrection><Notes/><ShowCreatedDateAsRegisteredDate>False</ShowCreatedDateAsRegisteredDate></Interest><Interest Id="20051" ParentId="" LastAmendment="2015-06-02T10:46:49" LastAmendmentType="C"><RegisteredInterest>Two commercial properties, both of which are small industrial units on a business park in North Yorkshire, owned by DM Electronics Ltd. </RegisteredInterest><RegisteredLate>False</RegisteredLate><Created>2015-06-02T00:00:00</Created><Amended xsi:nil="true" xmlns:xsi="http://www.w3.org/2001/XMLSchema-instance"/><Deleted xsi:nil="true" xmlns:xsi="http://www.w3.org/2001/XMLSchema-instance"/><IsCorrection>False</IsCorrection><Notes/><ShowCreatedDateAsRegisteredDate>True</ShowCreatedDateAsRegisteredDate></Interest></Category><Category Id="25" Name="7. (i) Shareholdings: over 15% of issued share capital"><Interest Id="20050" ParentId="" LastAmendment="2015-06-02T10:45:23" LastAmendmentType="C"><RegisteredInterest>DM Electronics Ltd, electronics design and manufacturing. </RegisteredInterest><RegisteredLate>False</RegisteredLate><Created>2015-06-02T00:00:00</Created><Amended xsi:nil="true" xmlns:xsi="http://www.w3.org/2001/XMLSchema-instance"/><Deleted xsi:nil="true" xmlns:xsi="http://www.w3.org/2001/XMLSchema-instance"/><IsCorrection>False</IsCorrection><Notes/><ShowCreatedDateAsRegisteredDate>True</ShowCreatedDateAsRegisteredDate></Interest></Category></Interests><Staffing/><Addresses><Address Type_Id="1"><Type>Parliamentary</Type><IsPreferred>False</IsPreferred><IsPhysical>True</IsPhysical><Note></Note><Address1>House of Commons</Address1><Address2/><Address3/><Address4/><Address5>London</Address5><Postcode>SW1A 0AA</Postcode><Phone>020 7219 8784</Phone><Fax/><Email>wendy.morton.mp@parliament.uk</Email><OtherAddress/></Address><Address Type_Id="7"><Type>Twitter</Type><IsPreferred>False</IsPreferred><IsPhysical>False</IsPhysical><Note/><Address1>https://twitter.com/morton_wendy</Address1></Address><Address Type_Id="6"><Type>Website</Type><IsPreferred>False</IsPreferred><IsPhysical>False</IsPhysical><Note/><Address1>http://wendymorton.co.uk/</Address1></Address></Addresses><KnownAs/><BiographyEntries/><Experiences/></Member></Members>